{
"meta":{"test_sets":[],"test_metrics":[],"learn_metrics":[{"best_value":"Min","name":"RMSE"}],"launch_mode":"Train","parameters":"","iteration_count":150,"learn_sets":["learn"],"name":"experiment"},
"iterations":[
{"learn":[126.2228603],"iteration":0,"passed_time":0.01149100928,"remaining_time":1.712160382},
{"learn":[71.13844057],"iteration":1,"passed_time":0.02183490571,"remaining_time":1.615783022},
{"learn":[40.02241633],"iteration":2,"passed_time":0.03271519436,"remaining_time":1.603044523},
{"learn":[22.35887595],"iteration":3,"passed_time":0.04406226832,"remaining_time":1.608272794},
{"learn":[12.56189462],"iteration":4,"passed_time":0.05450670155,"remaining_time":1.580694345},
{"learn":[6.996025334],"iteration":5,"passed_time":0.06812738591,"remaining_time":1.635057262},
{"learn":[3.942448659],"iteration":6,"passed_time":0.08237945435,"remaining_time":1.682894567},
{"learn":[2.225075038],"iteration":7,"passed_time":0.09759272611,"remaining_time":1.732270889},
{"learn":[1.241416237],"iteration":8,"passed_time":0.1134335481,"remaining_time":1.777125587},
{"learn":[0.7120801076],"iteration":9,"passed_time":0.1305489952,"remaining_time":1.827685932},
{"learn":[0.4037088884],"iteration":10,"passed_time":0.1474414392,"remaining_time":1.863123641},
{"learn":[0.228595488],"iteration":11,"passed_time":0.1666652606,"remaining_time":1.916650497},
{"learn":[0.1296402725],"iteration":12,"passed_time":0.183728651,"remaining_time":1.936217322},
{"learn":[0.07600142568],"iteration":13,"passed_time":0.2004943771,"remaining_time":1.947659664},
{"learn":[0.04232692341],"iteration":14,"passed_time":0.2167847748,"remaining_time":1.951062973},
{"learn":[0.02357282691],"iteration":15,"passed_time":0.2318609122,"remaining_time":1.941835139},
{"learn":[0.01340680894],"iteration":16,"passed_time":0.2492458306,"remaining_time":1.949982087},
{"learn":[0.007638799649],"iteration":17,"passed_time":0.2634150947,"remaining_time":1.931710694},
{"learn":[0.004311661373],"iteration":18,"passed_time":0.2777348095,"remaining_time":1.914908423},
{"learn":[0.002456325626],"iteration":19,"passed_time":0.2965195451,"remaining_time":1.927377043},
{"learn":[0.001379552766],"iteration":20,"passed_time":0.3107949308,"remaining_time":1.90916886},
{"learn":[0.0008265396714],"iteration":21,"passed_time":0.3327316874,"remaining_time":1.935893454},
{"learn":[0.0004818807246],"iteration":22,"passed_time":0.3577079221,"remaining_time":1.975169831},
{"learn":[0.0002962017354],"iteration":23,"passed_time":0.3746455894,"remaining_time":1.966889344},
{"learn":[0.0001722780578],"iteration":24,"passed_time":0.3874132615,"remaining_time":1.937066308},
{"learn":[0.0001054704106],"iteration":25,"passed_time":0.4013285406,"remaining_time":1.914028424},
{"learn":[6.698001531e-05],"iteration":26,"passed_time":0.4143551413,"remaining_time":1.887617866},
{"learn":[4.180089358e-05],"iteration":27,"passed_time":0.4259710411,"remaining_time":1.856016679},
{"learn":[2.360449717e-05],"iteration":28,"passed_time":0.4392534463,"remaining_time":1.832747138},
{"learn":[1.359860503e-05],"iteration":29,"passed_time":0.4514557065,"remaining_time":1.805822826},
{"learn":[7.761609285e-06],"iteration":30,"passed_time":0.4629854973,"remaining_time":1.777266909},
{"learn":[4.704737986e-06],"iteration":31,"passed_time":0.4735284296,"remaining_time":1.746136084},
{"learn":[2.954861614e-06],"iteration":32,"passed_time":0.4846987716,"remaining_time":1.718477463},
{"learn":[1.710950529e-06],"iteration":33,"passed_time":0.4955031778,"remaining_time":1.690540254},
{"learn":[1.053920285e-06],"iteration":34,"passed_time":0.5053751552,"remaining_time":1.660518367},
{"learn":[5.906992075e-07],"iteration":35,"passed_time":0.5175920888,"remaining_time":1.639041615},
{"learn":[3.671128343e-07],"iteration":36,"passed_time":0.5285897582,"remaining_time":1.614341694},
{"learn":[2.281434714e-07],"iteration":37,"passed_time":0.5377854199,"remaining_time":1.585051764},
{"learn":[1.274407212e-07],"iteration":38,"passed_time":0.5492300979,"remaining_time":1.563193355},
{"learn":[7.209139974e-08],"iteration":39,"passed_time":0.5595684329,"remaining_time":1.53881319},
{"learn":[4.040996285e-08],"iteration":40,"passed_time":0.5712997437,"remaining_time":1.51882127},
{"learn":[2.285758612e-08],"iteration":41,"passed_time":0.5826634499,"remaining_time":1.498277443},
{"learn":[1.370461314e-08],"iteration":42,"passed_time":0.5931547784,"remaining_time":1.475989797},
{"learn":[8.77552073e-09],"iteration":43,"passed_time":0.6043465613,"remaining_time":1.455925807},
{"learn":[5.179421712e-09],"iteration":44,"passed_time":0.614634161,"remaining_time":1.434146376},
{"learn":[3.166224638e-09],"iteration":45,"passed_time":0.6248428198,"remaining_time":1.412688114},
{"learn":[1.768769783e-09],"iteration":46,"passed_time":0.6365967881,"remaining_time":1.395095089},
{"learn":[9.893270028e-10],"iteration":47,"passed_time":0.6489441116,"remaining_time":1.379006237},
{"learn":[5.554900639e-10],"iteration":48,"passed_time":0.6612936108,"remaining_time":1.363074586},
{"learn":[3.138892633e-10],"iteration":49,"passed_time":0.6719461793,"remaining_time":1.343892359},
{"learn":[1.809137634e-10],"iteration":50,"passed_time":0.683439999,"remaining_time":1.326677645},
{"learn":[1.211214797e-10],"iteration":51,"passed_time":0.6940149089,"remaining_time":1.307951174},
{"learn":[6.850607317e-11],"iteration":52,"passed_time":0.7055704135,"remaining_time":1.291326983},
{"learn":[3.997450389e-11],"iteration":53,"passed_time":0.7171197837,"remaining_time":1.274879615},
{"learn":[2.23001013e-11],"iteration":54,"passed_time":0.7276685051,"remaining_time":1.256881963},
{"learn":[1.247139618e-11],"iteration":55,"passed_time":0.7374146519,"remaining_time":1.237803166},
{"learn":[7.107255699e-12],"iteration":56,"passed_time":0.747894698,"remaining_time":1.220249244},
{"learn":[4.044973069e-12],"iteration":57,"passed_time":0.7595802285,"remaining_time":1.204851397},
{"learn":[2.261929164e-12],"iteration":58,"passed_time":0.7704414745,"remaining_time":1.188308037},
{"learn":[1.27039564e-12],"iteration":59,"passed_time":0.7811969772,"remaining_time":1.171795466},
{"learn":[7.162743552e-13],"iteration":60,"passed_time":0.791967647,"remaining_time":1.15549378},
{"learn":[4.006611141e-13],"iteration":61,"passed_time":0.8024371854,"remaining_time":1.138943102},
{"learn":[2.223086659e-13],"iteration":62,"passed_time":0.8138667735,"remaining_time":1.123911259},
{"learn":[1.254432611e-13],"iteration":63,"passed_time":0.8259378772,"remaining_time":1.109854022},
{"learn":[7.517013835e-14],"iteration":64,"passed_time":0.8365418168,"remaining_time":1.093939299},
{"learn":[5.115452584e-14],"iteration":65,"passed_time":0.847344177,"remaining_time":1.078438043},
{"learn":[4.284657204e-14],"iteration":66,"passed_time":0.8582006251,"remaining_time":1.063144058},
{"learn":[3.938594284e-14],"iteration":67,"passed_time":0.8689054221,"remaining_time":1.047797715},
{"learn":[3.863794663e-14],"iteration":68,"passed_time":0.8795018757,"remaining_time":1.032458724},
{"learn":[3.832639843e-14],"iteration":69,"passed_time":0.890631614,"remaining_time":1.017864702},
{"learn":[3.826624506e-14],"iteration":70,"passed_time":0.9022185739,"remaining_time":1.003877005},
{"learn":[3.825456874e-14],"iteration":71,"passed_time":0.9136965254,"remaining_time":0.9898379025},
{"learn":[3.825147095e-14],"iteration":72,"passed_time":0.9247589201,"remaining_time":0.9754306417},
{"learn":[3.825147676e-14],"iteration":73,"passed_time":0.9353259809,"remaining_time":0.9606050615},
{"learn":[3.824959083e-14],"iteration":74,"passed_time":0.94782694,"remaining_time":0.94782694},
{"learn":[3.82496707e-14],"iteration":75,"passed_time":0.9587600029,"remaining_time":0.9335294765},
{"learn":[3.824999534e-14],"iteration":76,"passed_time":0.968665814,"remaining_time":0.918345512},
{"learn":[3.82499923e-14],"iteration":77,"passed_time":0.9785621747,"remaining_time":0.9032881612},
{"learn":[3.824999136e-14],"iteration":78,"passed_time":0.9883397403,"remaining_time":0.8882547033},
{"learn":[3.824999106e-14],"iteration":79,"passed_time":0.9988818422,"remaining_time":0.8740216119},
{"learn":[3.824999097e-14],"iteration":80,"passed_time":1.009336032,"remaining_time":0.8598047681},
{"learn":[3.824999094e-14],"iteration":81,"passed_time":1.01963996,"remaining_time":0.8455550888},
{"learn":[3.824999094e-14],"iteration":82,"passed_time":1.029712319,"remaining_time":0.8312135584},
{"learn":[3.824999093e-14],"iteration":83,"passed_time":1.040543691,"remaining_time":0.8175700427},
{"learn":[3.824999093e-14],"iteration":84,"passed_time":1.050847557,"remaining_time":0.8035893086},
{"learn":[3.824999093e-14],"iteration":85,"passed_time":1.062323125,"remaining_time":0.7905660468},
{"learn":[3.824999093e-14],"iteration":86,"passed_time":1.073035496,"remaining_time":0.7770257043},
{"learn":[3.824999093e-14],"iteration":87,"passed_time":1.083774715,"remaining_time":0.7635685491},
{"learn":[3.824999093e-14],"iteration":88,"passed_time":1.093303053,"remaining_time":0.7493425423},
{"learn":[3.824999093e-14],"iteration":89,"passed_time":1.10378955,"remaining_time":0.7358596999},
{"learn":[3.824999093e-14],"iteration":90,"passed_time":1.114471417,"remaining_time":0.7225693805},
{"learn":[3.824999093e-14],"iteration":91,"passed_time":1.125196561,"remaining_time":0.7093630491},
{"learn":[3.824999093e-14],"iteration":92,"passed_time":1.135910899,"remaining_time":0.6962034541},
{"learn":[3.824999093e-14],"iteration":93,"passed_time":1.145808344,"remaining_time":0.6826092262},
{"learn":[3.824999093e-14],"iteration":94,"passed_time":1.155953461,"remaining_time":0.669236214},
{"learn":[3.824999093e-14],"iteration":95,"passed_time":1.16599034,"remaining_time":0.655869566},
{"learn":[3.824999093e-14],"iteration":96,"passed_time":1.176094037,"remaining_time":0.6426080822},
{"learn":[3.824999093e-14],"iteration":97,"passed_time":1.186504546,"remaining_time":0.6295738406},
{"learn":[3.824999093e-14],"iteration":98,"passed_time":1.195819365,"remaining_time":0.6160281576},
{"learn":[3.824999093e-14],"iteration":99,"passed_time":1.205527568,"remaining_time":0.6027637841},
{"learn":[3.824999093e-14],"iteration":100,"passed_time":1.215774201,"remaining_time":0.5898310481},
{"learn":[3.824999093e-14],"iteration":101,"passed_time":1.225480632,"remaining_time":0.5766967682},
{"learn":[3.824999093e-14],"iteration":102,"passed_time":1.237049275,"remaining_time":0.5644787956},
{"learn":[3.824999093e-14],"iteration":103,"passed_time":1.248131306,"remaining_time":0.5520580776},
{"learn":[3.824999093e-14],"iteration":104,"passed_time":1.258500041,"remaining_time":0.5393571602},
{"learn":[3.824999093e-14],"iteration":105,"passed_time":1.268320687,"remaining_time":0.5264727379},
{"learn":[3.824999093e-14],"iteration":106,"passed_time":1.279180639,"remaining_time":0.5140632473},
{"learn":[3.824999093e-14],"iteration":107,"passed_time":1.289835806,"remaining_time":0.5016028135},
{"learn":[3.824999093e-14],"iteration":108,"passed_time":1.300105731,"remaining_time":0.489030596},
{"learn":[3.824999093e-14],"iteration":109,"passed_time":1.309651091,"remaining_time":0.4762367603},
{"learn":[3.824999093e-14],"iteration":110,"passed_time":1.320058125,"remaining_time":0.4638042061},
{"learn":[3.824999093e-14],"iteration":111,"passed_time":1.329866429,"remaining_time":0.4512046814},
{"learn":[3.824999093e-14],"iteration":112,"passed_time":1.339314883,"remaining_time":0.4385367314},
{"learn":[3.824999093e-14],"iteration":113,"passed_time":1.349136066,"remaining_time":0.4260429683},
{"learn":[3.824999093e-14],"iteration":114,"passed_time":1.35887977,"remaining_time":0.4135721041},
{"learn":[3.824999093e-14],"iteration":115,"passed_time":1.369080113,"remaining_time":0.4012821021},
{"learn":[3.824999093e-14],"iteration":116,"passed_time":1.379104351,"remaining_time":0.3889781502},
{"learn":[3.824999093e-14],"iteration":117,"passed_time":1.387984061,"remaining_time":0.3764024573},
{"learn":[3.824999093e-14],"iteration":118,"passed_time":1.39762563,"remaining_time":0.364087349},
{"learn":[3.824999093e-14],"iteration":119,"passed_time":1.407182688,"remaining_time":0.3517956719},
{"learn":[3.824999093e-14],"iteration":120,"passed_time":1.416792326,"remaining_time":0.3395617972},
{"learn":[3.824999093e-14],"iteration":121,"passed_time":1.426267568,"remaining_time":0.3273400976},
{"learn":[3.824999093e-14],"iteration":122,"passed_time":1.435339647,"remaining_time":0.3150745566},
{"learn":[3.824999093e-14],"iteration":123,"passed_time":1.444811821,"remaining_time":0.302944414},
{"learn":[3.824999093e-14],"iteration":124,"passed_time":1.454330743,"remaining_time":0.2908661486},
{"learn":[3.824999093e-14],"iteration":125,"passed_time":1.464456461,"remaining_time":0.2789440877},
{"learn":[3.824999093e-14],"iteration":126,"passed_time":1.474327867,"remaining_time":0.2670042593},
{"learn":[3.824999093e-14],"iteration":127,"passed_time":1.484907185,"remaining_time":0.2552184224},
{"learn":[3.824999093e-14],"iteration":128,"passed_time":1.495062216,"remaining_time":0.2433822211},
{"learn":[3.824999093e-14],"iteration":129,"passed_time":1.504361656,"remaining_time":0.2314402548},
{"learn":[3.824999093e-14],"iteration":130,"passed_time":1.514912196,"remaining_time":0.2197200895},
{"learn":[3.824999093e-14],"iteration":131,"passed_time":1.524647416,"remaining_time":0.2079064658},
{"learn":[3.824999093e-14],"iteration":132,"passed_time":1.53497324,"remaining_time":0.1961995871},
{"learn":[3.824999093e-14],"iteration":133,"passed_time":1.545193979,"remaining_time":0.1845007736},
{"learn":[3.824999093e-14],"iteration":134,"passed_time":1.554451117,"remaining_time":0.1727167908},
{"learn":[3.824999093e-14],"iteration":135,"passed_time":1.564420334,"remaining_time":0.1610432696},
{"learn":[3.824999093e-14],"iteration":136,"passed_time":1.575027694,"remaining_time":0.1494551827},
{"learn":[3.824999093e-14],"iteration":137,"passed_time":1.584914767,"remaining_time":0.1378186754},
{"learn":[3.824999093e-14],"iteration":138,"passed_time":1.594675961,"remaining_time":0.1261973782},
{"learn":[3.824999093e-14],"iteration":139,"passed_time":1.603940717,"remaining_time":0.1145671941},
{"learn":[3.824999093e-14],"iteration":140,"passed_time":1.614266516,"remaining_time":0.1030382883},
{"learn":[3.824999093e-14],"iteration":141,"passed_time":1.624594034,"remaining_time":0.09152642443},
{"learn":[3.824999093e-14],"iteration":142,"passed_time":1.635492333,"remaining_time":0.08005906526},
{"learn":[3.824999093e-14],"iteration":143,"passed_time":1.646231234,"remaining_time":0.0685929681},
{"learn":[3.824999093e-14],"iteration":144,"passed_time":1.656195523,"remaining_time":0.05711019045},
{"learn":[3.824999093e-14],"iteration":145,"passed_time":1.666646172,"remaining_time":0.04566153895},
{"learn":[3.824999093e-14],"iteration":146,"passed_time":1.677175418,"remaining_time":0.03422806975},
{"learn":[3.824999093e-14],"iteration":147,"passed_time":1.689128222,"remaining_time":0.02282605705},
{"learn":[3.824999093e-14],"iteration":148,"passed_time":1.699751565,"remaining_time":0.01140772862},
{"learn":[3.824999093e-14],"iteration":149,"passed_time":1.710076905,"remaining_time":0}
]}